clean_folder/__init__.py
clean_folder/sort.py
sort_file_by_extension-1.0.7.dist-info/License
sort_file_by_extension-1.0.7.dist-info/METADATA
sort_file_by_extension-1.0.7.dist-info/WHEEL
sort_file_by_extension-1.0.7.dist-info/entry_points.txt
sort_file_by_extension-1.0.7.dist-info/top_level.txt
sort_file_by_extension-1.0.7.dist-info/RECORD
